README.rst
setup.py
terragon/__init__.py
terragon/sparkle.py
terragon/terragon.py
terragon/xrange_helper.py
terragon.egg-info/PKG-INFO
terragon.egg-info/SOURCES.txt
terragon.egg-info/dependency_links.txt
terragon.egg-info/top_level.txt