Metadata-Version: 1.0
Name: terragon
Version: 0.3.1
Summary: a better pickle
Home-page: https://github.com/yhat/terragon/
Author: Greg Lamp
Author-email: greg@yhathq.com
License: BSD
Platform: UNKNOWN
